{
  "timestamp": "2025-10-06T21:37:02.745551",
  "ticker": "AMAT",
  "data_points": 2510,
  "latest_signal": {
    "date": "2025-10-06",
    "signal": "HOLD",
    "position": "FLAT",
    "phase_quadrant": "Quadrante 3 (Picco -> Discesa)",
    "phase_value": 0.6805237447197862,
    "oscillator_value": 29.795125000000013,
    "signal_strength": 84.56248250185806,
    "confidence": "HIGH",
    "price": 223.91,
    "timestamp": "2025-10-06T21:37:01.681167"
  },
  "backtest_metrics": {
    "total_return_%": 188.9459297594285,
    "max_drawdown_%": 4.212147894205256,
    "sharpe_ratio": 1.5170932536700792,
    "sortino_ratio": 1.2538148845253478,
    "calmar_ratio": 9.115788443504298,
    "total_trades": 13,
    "win_rate_%": 84.61538461538461,
    "profit_factor": 17.291108365901586
  },
  "cycle_analysis": {
    "dominant_period": 84.0,
    "p_value": 0.0,
    "significant": "True"
  }
}